resim/__init__.py
resim/command_line.py
resim/core.py
resim/plot.py
resim/flask/__init__.py
resim/flask/flaskapp.py
resim/flask/resim_compute.py
resim/flask/resim_form.py
resim/flask/resim_plot.py
resim/flask/templates/404.html
resim/flask/templates/500.html
resim/flask/templates/about.html
resim/flask/templates/docs.html
resim/flask/templates/download.html
resim/flask/templates/index.html
resim/flask/templates/layout.html
resim/flask/templates/resim_dash.html
resim-0.1.1.dist-info/DESCRIPTION.rst
resim-0.1.1.dist-info/METADATA
resim-0.1.1.dist-info/RECORD
resim-0.1.1.dist-info/WHEEL
resim-0.1.1.dist-info/entry_points.txt
resim-0.1.1.dist-info/metadata.json
resim-0.1.1.dist-info/top_level.txt
