Metadata-Version: 2.0
Name: resim
Version: 0.1.1
Summary: chemoREsistance SIMulator
Home-page: http://github.com/zeochoy/resim
Author: Zeo Choy
Author-email: zeochoy@gmail.com
License: MIT
Keywords: chemoresistance cancer outcome simulations modeling
Platform: UNKNOWN
Classifier: Development Status :: 4 - Beta
Classifier: Intended Audience :: Developers
Classifier: Topic :: Scientific/Engineering :: Medical Science Apps.
Classifier: License :: OSI Approved :: MIT License
Classifier: Programming Language :: Python :: 2
Classifier: Programming Language :: Python :: 2.7
Classifier: Environment :: Console
Requires-Dist: Flask-WTF
Requires-Dist: flask
Requires-Dist: matplotlib
Requires-Dist: numpy
Requires-Dist: pandas
Requires-Dist: plotly
Requires-Dist: scipy
Requires-Dist: sdeint
Requires-Dist: seaborn
